kyws/__init__.py
kyws/alchemist.py
kyws/backtester.py
kyws/backtraderTest.py
kyws/backtraderTest_multi.py
kyws/backtraderTest_single.py
kyws/binanceBot.py
kyws/binanceTest2.py
kyws/binanceTest_2ema.py
kyws/bybitBot.py
kyws/bybitBot_BTC.py
kyws/screener.py
kyws/screener_div_backup.py
kyws/screener_tushare.py
kyws/BinanceBot/bn3ema.py
kyws/BinanceBot/bn3ema_backup.py
kyws/BinanceBot/config.py
kyws/BinanceBot/fetchPairs.py
kyws/BinanceBot/teleBot.py
kyws/DrXiongAPI/dataPrep.py
kyws/EastMoneyAPI/dataPrep.py
kyws-0.0.1.dist-info/METADATA
kyws-0.0.1.dist-info/WHEEL
kyws-0.0.1.dist-info/licenses/LICENSE
kyws-0.0.1.dist-info/RECORD
