Metadata-Version: 2.3
Name: kyws
Version: 0.0.1
Summary: Kai Yuan Wang Shi
Project-URL: Source, https://github.com/foolmuyi/WealthPassword
Project-URL: Repository, https://github.com/foolmuyi/WealthPassword
Author-email: DeBiao <muyiorlk@gmail.com>
Maintainer-email: DeBiao <muyiorlk@gmail.com>
License: MIT License
License-File: LICENSE
Classifier: License :: OSI Approved :: MIT License
Classifier: Programming Language :: Python
Requires-Python: >=3.5
Requires-Dist: backtrader
Requires-Dist: eth-account
Requires-Dist: numpy
Requires-Dist: pandas
Requires-Dist: requests
Requires-Dist: telegram
Requires-Dist: web3
